my_best_python_project/__init__.py
my_best_python_project/main.py
my_best_python_project/py.typed
my_best_python_project-0.2.0.dist-info/METADATA
my_best_python_project-0.2.0.dist-info/WHEEL
my_best_python_project-0.2.0.dist-info/entry_points.txt
my_best_python_project-0.2.0.dist-info/licenses/LICENSE
my_best_python_project-0.2.0.dist-info/RECORD
